Workbook

Sheet Raw_Data
A1: country | B1: country_code_x | C1: region | D1: income_level | E1: capital_city | F1: latitude | G1: longitude | H1: country_code_y | I1: inflation_year | J1: inflation_annual_pct | K1: cost_living_index | L1: rent_index | M1: groceries_index | N1: restaurants_index | O1: purchasing_power_index | P1: bread_price_usd | Q1: transport_oneway_usd | R1: transport_monthly_pass_usd | S1: rent_monthly_usd | T1: utilities_monthly_usd
A2: Aruba | C2: Latin America & Caribbean | D2: High income | E2: Oranjestad | F2: 12.5167 | G2: -70.0167
A3: Afghanistan | C3: Middle East, North Africa, Afghanistan & Pakistan | D3: Low income | E3: Kabul | F3: 34.5228 | G3: 69.1761 | H3: AFG | I3: 2024 | J3: -6.6011856 | K3: 38.2 | L3: 8.2 | M3: 36.8 | N3: 36.9 | O3: 48.5 | P3: 0.88 | Q3: 1.05 | R3: 12.8 | S3: 85 | T3: 20
A4: Angola | C4: Sub-Saharan Africa | D4: Lower middle income | E4: Luanda | F4: -8.81155 | G4: 13.242 | H4: AGO | I4: 2024 | J4: 28.240495
A5: Albania | C5: Europe & Central Asia | D5: Upper middle income | E5: Tirane | F5: 41.3317 | G5: 19.8172 | H5: ALB | I5: 2024 | J5: 2.2158738
A6: Andorra | C6: Europe & Central Asia | D6: High income | E6: Andorra la Vella | F6: 42.5075 | G6: 1.5218
A7: United Arab Emirates | C7: Middle East, North Africa, Afghanistan & Pakistan | D7: High income | E7: Abu Dhabi | F7: 24.4764 | G7: 54.3705 | H7: ARE | I7: 2024 | J7: 1.6633651 | K7: 72.4 | L7: 34.2 | M7: 68.5 | N7: 70.8 | O7: 96.2 | S7: 1100
A8: Argentina | C8: Latin America & Caribbean | D8: Upper middle income | E8: Buenos Aires | F8: -34.6118 | G8: -58.4173 | H8: ARG | I8: 2024 | J8: 219.88393
A9: Armenia | C9: Europe & Central Asia | D9: Upper middle income | E9: Yerevan | F9: 40.1596 | G9: 44.509 | H9: ARM | I9: 2024 | J9: 0.26951198
A10: American Samoa | C10: East Asia & Pacific | D10: High income | E10: Pago Pago | F10: -14.2846 | G10: -170.691
A11: Antigua and Barbuda | C11: Latin America & Caribbean | D11: High income | E11: Saint John's | F11: 17.1175 | G11: -61.8456 | H11: ATG | I11: 2024 | J11: 6.198867
A12: Australia | C12: East Asia & Pacific | D12: High income | E12: Canberra | F12: -35.282 | G12: 149.129 | H12: AUS | I12: 2024 | J12: 3.1665667 | K12: 69.5 | L12: 32.8 | M12: 65.4 | N12: 68.9 | O12: 95.6 | P12: 3.25 | S12: 1450 | T12: 140
A13: Austria | C13: Europe & Central Asia | D13: High income | E13: Vienna | F13: 48.2201 | G13: 16.3798 | H13: AUT | I13: 2024 | J13: 2.9379157
A14: Azerbaijan | C14: Europe & Central Asia | D14: Upper middle income | E14: Baku | F14: 40.3834 | G14: 49.8932 | H14: AZE | I14: 2024 | J14: 2.2121719 | P14: 0.46
A15: Burundi | C15: Sub-Saharan Africa | D15: Low income | E15: Bujumbura | F15: -3.3784 | G15: 29.3639 | H15: BDI | I15: 2024 | J15: 20.212493
A16: Belgium | C16: Europe & Central Asia | D16: High income | E16: Brussels | F16: 50.8371 | G16: 4.36761 | H16: BEL | I16: 2024 | J16: 3.1434914
A17: Benin | C17: Sub-Saharan Africa | D17: Lower middle income | E17: Porto-Novo | F17: 6.4779 | G17: 2.6323 | H17: BEN | I17: 2024 | J17: 1.1609309
A18: Burkina Faso | C18: Sub-Saharan Africa | D18: Low income | E18: Ouagadougou | F18: 12.3605 | G18: -1.53395 | H18: BFA | I18: 2024 | J18: 4.1908172
A19: Bangladesh | C19: South Asia | D19: Lower middle income | E19: Dhaka | F19: 23.7055 | G19: 90.4113 | H19: BGD | I19: 2024 | J19: 10.465748 | K19: 39.5 | L19: 8.8 | M19: 38.1 | N19: 38.2 | O19: 50.8 | P19: 0.95 | Q19: 1.18 | R19: 14.5 | S19: 100 | T19: 25
A20: Bulgaria | C20: Europe & Central Asia | D20: High income | E20: Sofia | F20: 42.7105 | G20: 23.3238 | H20: BGR | I20: 2024 | J20: 2.4465194
A21: Bahrain | C21: Middle East, North Africa, Afghanistan & Pakistan | D21: High income | E21: Manama | F21: 26.1921 | G21: 50.5354 | H21: BHR | I21: 2024 | J21: 0.91963546 | K21: 65.2 | L21: 26.1 | M21: 61.8 | N21: 63.5 | O21: 86.2 | S21: 600
A22: Bahamas, The | C22: Latin America & Caribbean | D22: High income | E22: Nassau | F22: 25.0661 | G22: -77.339 | H22: BHS | I22: 2024 | J22: 0.40916249
A23: Bosnia and Herzegovina | C23: Europe & Central Asia | D23: Upper middle income | E23: Sarajevo | F23: 43.8607 | G23: 18.4214 | H23: BIH | I23: 2023 | J23: 6.1059011
A24: Belarus | C24: Europe & Central Asia | D24: Upper middle income | E24: Minsk | F24: 53.9678 | G24: 27.5766 | H24: BLR | I24: 2024 | J24: 5.7853191
A25: Belize | C25: Latin America & Caribbean | D25: Upper middle income | E25: Belmopan | F25: 17.2534 | G25: -88.7713 | H25: BLZ | I25: 2024 | J25: 3.2895599
A26: Bermuda | C26: North America | D26: High income | E26: Hamilton | F26: 32.3293 | G26: -64.706 | P26: 8.61
A27: Bolivia | C27: Latin America & Caribbean | D27: Lower middle income | E27: La Paz | F27: -13.9908 | G27: -66.1936 | H27: BOL | I27: 2024 | J27: 5.0997657
A28: Brazil | C28: Latin America & Caribbean | D28: Upper middle income | E28: Brasilia | F28: -15.7801 | G28: -47.9292 | H28: BRA | I28: 2024 | J28: 4.3674641 | K28: 51.4 | L28: 15.9 | M28: 49.2 | N28: 50.1 | O28: 67.5 | P28: 1.85 | Q28: 2.85 | R28: 52.4 | S28: 270 | T28: 70
A29: Barbados | C29: Latin America & Caribbean | D29: High income | E29: Bridgetown | F29: 13.0935 | G29: -59.6105 | H29: BRB | I29: 2024 | J29: 1.4464366 | K29: 75.2 | L29: 41.8 | M29: 70.8 | N29: 73.2 | O29: 88.5 | S29: 1200
A30: Brunei Darussalam | C30: East Asia & Pacific | D30: High income | E30: Bandar Seri Begawan | F30: 4.94199 | G30: 114.946 | H30: BRN | I30: 2024 | J30: -0.38867417
A31: Bhutan | C31: South Asia | D31: Lower middle income | E31: Thimphu | F31: 27.5768 | G31: 89.6177 | H31: BTN | I31: 2024 | J31: 2.7613157
A32: Botswana | C32: Sub-Saharan Africa | D32: Upper middle income | E32: Gaborone | F32: -24.6544 | G32: 25.9201 | H32: BWA | I32: 2024 | J32: 2.8183513
A33: Central African Republic | C33: Sub-Saharan Africa | D33: Low income | E33: Bangui | F33: 5.63056 | G33: 21.6407 | H33: CAF | I33: 2024 | J33: 1.477336
A34: Canada | C34: North America | D34: High income | E34: Ottawa | F34: 45.4215 | G34: -75.6919 | H34: CAN | I34: 2024 | J34: 2.3815838 | K34: 65.4 | L34: 28.4 | M34: 61.5 | N34: 64.2 | O34: 92.1 | P34: 3.18 | S34: 1200 | T34: 145
A35: Switzerland | C35: Europe & Central Asia | D35: High income | E35: Bern | F35: 46.948 | G35: 7.44821 | H35: CHE | I35: 2024 | J35: 1.0623404 | K35: 82.3 | L35: 50.1 | M35: 75.2 | N35: 88.4 | O35: 120.5 | P35: 3.81 | Q35: 6.36 | R35: 149.7 | S35: 1850 | T35: 220
A36: Channel Islands | C36: Europe & Central Asia | D36: High income
A37: Chile | C37: Latin America & Caribbean | D37: High income | E37: Santiago | F37: -33.475 | G37: -70.6475 | H37: CHL | I37: 2024 | J37: 4.2976389
A38: China | C38: East Asia & Pacific | D38: Upper middle income | E38: Beijing | F38: 40.0495 | G38: 116.286 | H38: CHN | I38: 2024 | J38: 0.21812894 | K38: 49.8 | L38: 14.8 | M38: 47.8 | N38: 48.5 | O38: 64.2 | P38: 1.65 | Q38: 2.45 | R38: 42.8 | S38: 540 | T38: 80
A39: Cote d'Ivoire | C39: Sub-Saharan Africa | D39: Lower middle income | E39: Yamoussoukro | F39: 5.332 | G39: -4.0305 | H39: CIV | I39: 2024 | J39: 3.4505303
A40: Cameroon | C40: Sub-Saharan Africa | D40: Lower middle income | E40: Yaounde | F40: 3.8721 | G40: 11.5174 | H40: CMR | I40: 2024 | J40: 4.5333135
A41: Congo, Dem. Rep. | C41: Sub-Saharan Africa | D41: Low income | E41: Kinshasa | F41: -4.325 | G41: 15.3222
A42: Congo, Rep. | C42: Sub-Saharan Africa | D42: Lower middle income | E42: Brazzaville | F42: -4.2767 | G42: 15.2662 | H42: COG | I42: 2024 | J42: 3.0914363
A43: Colombia | C43: Latin America & Caribbean | D43: Upper middle income | E43: Bogota | F43: 4.60987 | G43: -74.082 | H43: COL | I43: 2024 | J43: 6.6090859
A44: Comoros | C44: Sub-Saharan Africa | D44: Lower middle income | E44: Moroni | F44: -11.6986 | G44: 43.2418 | H44: COM | I44: 2024 | J44: 5.0519261
A45: Cabo Verde | C45: Sub-Saharan Africa | D45: Upper middle income | E45: Praia | F45: 14.9218 | G45: -23.5087 | H45: CPV | I45: 2024 | J45: 1.04817
A46: Costa Rica | C46: Latin America & Caribbean | D46: High income | E46: San Jose | F46: 9.63701 | G46: -84.0089 | H46: CRI | I46: 2024 | J46: -0.412853
A47: Cuba | C47: Latin America & Caribbean | D47: Upper middle income | E47: Havana | F47: 23.1333 | G47: -82.3667
A48: Curacao | C48: Latin America & Caribbean | D48: High income | E48: Willemstad
A49: Cayman Islands | C49: Latin America & Caribbean | D49: High income | E49: George Town | F49: 19.3022 | G49: -81.3857 | K49: 94.3 | L49: 60.2 | M49: 85.6 | N49: 92.1 | O49: 115.8 | P49: 6.36 | S49: 2500
A50: Cyprus | C50: Europe & Central Asia | D50: High income | E50: Nicosia | F50: 35.1676 | G50: 33.3736 | H50: CYP | I50: 2024 | J50: 1.8002302
A51: Czechia | C51: Europe & Central Asia | D51: High income | E51: Prague | F51: 50.0878 | G51: 14.4205 | H51: CZE | I51: 2024 | J51: 2.435312
A52: Germany | C52: Europe & Central Asia | D52: High income | E52: Berlin | F52: 52.5235 | G52: 13.4115 | H52: DEU | I52: 2024 | J52: 2.2564981 | K52: 64.1 | L52: 26.5 | M52: 59.7 | N52: 62.8 | O52: 91.3 | P52: 2.72 | Q52: 4.85 | R52: 112.3 | S52: 850 | T52: 170
A53: Djibouti | C53: Middle East, North Africa, Afghanistan & Pakistan | D53: Lower middle income | E53: Djibouti | F53: 11.5806 | G53: 43.1425 | H53: DJI | I53: 2024 | J53: 2.1120117 | P53: 9.53
A54: Dominica | C54: Latin America & Caribbean | D54: Upper middle income | E54: Roseau | F54: 15.2976 | G54: -61.39 | H54: DMA | I54: 2024 | J54: 2.7362075
A55: Denmark | C55: Europe & Central Asia | D55: High income | E55: Copenhagen | F55: 55.6763 | G55: 12.5681 | H55: DNK | I55: 2024 | J55: 1.3722005 | K55: 72.1 | L55: 36.4 | M55: 67.2 | N55: 75.3 | O55: 102.8 | P55: 3.48 | Q55: 5.42 | R55: 128.5
A56: Dominican Republic | C56: Latin America & Caribbean | D56: Upper middle income | E56: Santo Domingo | F56: 18.479 | G56: -69.8908 | H56: DOM | I56: 2024 | J56: 3.3022334
A57: Algeria | C57: Middle East, North Africa, Afghanistan & Pakistan | D57: Upper middle income | E57: Algiers | F57: 36.7397 | G57: 3.05097 | H57: DZA | I57: 2024 | J57: 4.0461146
A58: Ecuador | C58: Latin America & Caribbean | D58: Upper middle income | E58: Quito | F58: -0.229498 | G58: -78.5243 | H58: ECU | I58: 2024 | J58: 1.5473252
A59: Egypt, Arab Rep. | C59: Middle East, North Africa, Afghanistan & Pakistan | D59: Lower middle income | E59: Cairo | F59: 30.0982 | G59: 31.2461 | H59: EGY | I59: 2024 | J59: 28.27059
A60: Eritrea | C60: Sub-Saharan Africa | D60: Low income | E60: Asmara | F60: 15.3315 | G60: 38.9183
A61: Spain | C61: Europe & Central Asia | D61: High income | E61: Madrid | F61: 40.4167 | G61: -3.70327 | H61: ESP | I61: 2024 | J61: 2.7471479 | K61: 60.8 | L61: 22.4 | M61: 56.8 | N61: 58.9 | O61: 82.1 | P61: 2.58 | Q61: 4.08 | R61: 92.6 | S61: 480 | T61: 95
A62: Estonia | C62: Europe & Central Asia | D62: High income | E62: Tallinn | F62: 59.4392 | G62: 24.7586 | H62: EST | I62: 2024 | J62: 3.5194119
A63: Ethiopia | C63: Sub-Saharan Africa | D63: Low income | E63: Addis Ababa | F63: 9.02274 | G63: 38.7468 | H63: ETH | I63: 2024 | J63: 21.037746
A64: Finland | C64: Europe & Central Asia | D64: High income | E64: Helsinki | F64: 60.1608 | G64: 24.9525 | H64: FIN | I64: 2024 | J64: 1.5656891 | Q64: 5.12 | R64: 118.6
A65: Fiji | C65: East Asia & Pacific | D65: Upper middle income | E65: Suva | F65: -18.1149 | G65: 178.399 | H65: FJI | I65: 2024 | J65: 3.8908424
A66: France | C66: Europe & Central Asia | D66: High income | E66: Paris | F66: 48.8566 | G66: 2.35097 | H66: FRA | I66: 2024 | J66: 1.9990494 | K66: 64.8 | L66: 27.9 | M66: 60.8 | N66: 63.5 | O66: 89.7 | P66: 2.78 | Q66: 4.62 | R66: 108.4 | S66: 738 | T66: 155
A67: Faroe Islands | C67: Europe & Central Asia | D67: High income | E67: Torshavn | F67: 61.8926 | G67: -6.91181
A68: Micronesia, Fed. Sts. | C68: East Asia & Pacific | D68: Upper middle income | E68: Palikir | F68: 6.91771 | G68: 158.185 | H68: FSM | I68: 2022 | J68: 5.4087438
A69: Gabon | C69: Sub-Saharan Africa | D69: Upper middle income | E69: Libreville | F69: 0.38832 | G69: 9.45162 | H69: GAB | I69: 2024 | J69: 1.17312
A70: United Kingdom | C70: Europe & Central Asia | D70: High income | E70: London | F70: 51.5002 | G70: -0.126236 | H70: GBR | I70: 2024 | J70: 3.2715729 | K70: 67.8 | L70: 30.5 | M70: 63.2 | N70: 66.7 | O70: 90.2 | P70: 3.12 | Q70: 4.48 | R70: 105.2 | S70: 1235 | T70: 160
A71: Georgia | C71: Europe & Central Asia | D71: Upper middle income | E71: Tbilisi | F71: 41.71 | G71: 44.793 | H71: GEO | I71: 2024 | J71: 1.1097176
A72: Ghana | C72: Sub-Saharan Africa | D72: Lower middle income | E72: Accra | F72: 5.57045 | G72: -0.20795 | H72: GHA | I72: 2024 | J72: 22.848328
A73: Gibraltar | C73: Europe & Central Asia | D73: High income
A74: Guinea | C74: Sub-Saharan Africa | D74: Lower middle income | E74: Conakry | F74: 9.51667 | G74: -13.7 | H74: GIN | I74: 2024 | J74: 8.1231391
A75: Gambia, The | C75: Sub-Saharan Africa | D75: Low income | E75: Banjul | F75: 13.4495 | G75: -16.5885 | H75: GMB | I75: 2024 | J75: 11.561053
A76: Guinea-Bissau | C76: Sub-Saharan Africa | D76: Low income | E76: Bissau | F76: 11.8037 | G76: -15.1804 | H76: GNB | I76: 2024 | J76: 3.7655583
A77: Equatorial Guinea | C77: Sub-Saharan Africa | D77: Upper middle income | E77: Malabo | F77: 3.7523 | G77: 8.7741 | H77: GNQ | I77: 2024 | J77: 2.9214023
A78: Greece | C78: Europe & Central Asia | D78: High income | E78: Athens | F78: 37.9792 | G78: 23.7166 | H78: GRC | I78: 2024 | J78: 2.7410188 | K78: 57.1 | L78: 19.2 | M78: 53.8 | N78: 55.1 | O78: 76.4 | P78: 2.38 | Q78: 3.62 | R78: 78.2 | S78: 380 | T78: 75
A79: Grenada | C79: Latin America & Caribbean | D79: Upper middle income | E79: Saint George's | F79: 12.0653 | G79: -61.7449 | H79: GRD | I79: 2024 | J79: 1.0861537
A80: Greenland | C80: Europe & Central Asia | D80: High income | E80: Nuuk | F80: 64.1836 | G80: -51.7214
A81: Guatemala | C81: Latin America & Caribbean | D81: Upper middle income | E81: Guatemala City | F81: 14.6248 | G81: -90.5328 | H81: GTM | I81: 2024 | J81: 2.8699275
A82: Guam | C82: East Asia & Pacific | D82: High income | E82: Agana | F82: 13.4443 | G82: 144.794
A83: Guyana | C83: Latin America & Caribbean | D83: High income | E83: Georgetown | F83: 6.80461 | G83: -58.1548 | H83: GUY | I83: 2024 | J83: 2.903795
A84: Hong Kong SAR, China | C84: East Asia & Pacific | D84: High income | F84: 22.3964 | G84: 114.109 | H84: HKG | I84: 2024 | J84: 1.7297212
A85: Honduras | C85: Latin America & Caribbean | D85: Lower middle income | E85: Tegucigalpa | F85: 15.1333 | G85: -87.4667 | H85: HND | I85: 2024 | J85: 4.606211
A86: Croatia | C86: Europe & Central Asia | D86: High income | E86: Zagreb | F86: 45.8069 | G86: 15.9614 | H86: HRV | I86: 2024 | J86: 2.9720048
A87: Haiti | C87: Latin America & Caribbean | D87: Lower middle income | E87: Port-au-Prince | F87: 18.5392 | G87: -72.3288 | H87: HTI | I87: 2024 | J87: 26.949056
A88: Hungary | C88: Europe & Central Asia | D88: High income | E88: Budapest | F88: 47.4984 | G88: 19.0408 | H88: HUN | I88: 2024 | J88: 3.7037037
A89: Indonesia | C89: East Asia & Pacific | D89: Upper middle income | E89: Jakarta | F89: -6.19752 | G89: 106.83 | H89: IDN | I89: 2024 | J89: 2.1815127 | K89: 47.2 | L89: 12.8 | M89: 45.1 | N89: 45.8 | O89: 60.8 | P89: 1.45 | Q89: 2.05 | R89: 32.4 | S89: 305 | T89: 55
A90: Isle of Man | C90: Europe & Central Asia | D90: High income | E90: Douglas | F90: 54.1509 | G90: -4.47928
A91: India | C91: South Asia | D91: Lower middle income | E91: New Delhi | F91: 28.6353 | G91: 77.225 | H91: IND | I91: 2024 | J91: 4.9530355 | K91: 48.5 | L91: 13.5 | M91: 46.2 | N91: 47.1 | O91: 62.5 | P91: 1.52 | Q91: 2.18 | R91: 35.2 | S91: 164 | T91: 45
A92: Ireland | C92: Europe & Central Asia | D92: High income | E92: Dublin | F92: 53.3441 | G92: -6.26749 | H92: IRL | I92: 2024 | J92: 2.11345 | K92: 68.9 | L92: 40.2 | M92: 64.7 | N92: 70.1 | O92: 92.4
A93: Iran, Islamic Rep. | C93: Middle East, North Africa, Afghanistan & Pakistan | D93: Upper middle income | E93: Tehran | F93: 35.6878 | G93: 51.4447 | H93: IRN | I93: 2024 | J93: 32.455871
A94: Iraq | C94: Middle East, North Africa, Afghanistan & Pakistan | D94: Upper middle income | E94: Baghdad | F94: 33.3302 | G94: 44.394 | H94: IRQ | I94: 2024 | J94: 2.6116961
A95: Iceland | C95: Europe & Central Asia | D95: High income | E95: Reykjavik | F95: 64.1353 | G95: -21.8952 | H95: ISL | I95: 2024 | J95: 5.8568385 | K95: 78.2 | L95: 45.6 | M95: 72.3 | N95: 82.1 | O95: 98.7 | P95: 4.26 | Q95: 7.94 | R95: 131.85
A96: Israel | C96: Middle East, North Africa, Afghanistan & Pakistan | D96: High income | F96: 31.7717 | G96: 35.2035 | H96: ISR | I96: 2024 | J96: 3.0748089
A97: Italy | C97: Europe & Central Asia | D97: High income | E97: Rome | F97: 41.8955 | G97: 12.4823 | H97: ITA | I97: 2024 | J97: 0.98237302 | K97: 62.5 | L97: 23.7 | M97: 58.2 | N97: 60.5 | O97: 83.6 | P97: 2.65 | Q97: 4.25 | R97: 98.5 | S97: 550 | T97: 110
A98: Jamaica | C98: Latin America & Caribbean | D98: Upper middle income | E98: Kingston | F98: 17.9927 | G98: -76.792 | H98: JAM | I98: 2024 | J98: 5.4119445
A99: Jordan | C99: Middle East, North Africa, Afghanistan & Pakistan | D99: Upper middle income | E99: Amman | F99: 31.9497 | G99: 35.9263 | H99: JOR | I99: 2024 | J99: 1.5565961
A100: Japan | C100: East Asia & Pacific | D100: High income | E100: Tokyo | F100: 35.67 | G100: 139.77 | H100: JPN | I100: 2024 | J100: 2.7385368 | K100: 63.2 | L100: 24.8 | M100: 58.9 | N100: 61.2 | O100: 85.4 | P100: 2.85 | S100: 750 | T100: 130
...

Sheet Clean_Data
A1: country | B1: region | C1: income_level | D1: capital_city | E1: latitude | F1: longitude | G1: inflation_year | H1: inflation_annual_pct | I1: cost_living_index | J1: rent_index | K1: groceries_index | L1: restaurants_index | M1: purchasing_power_index | N1: bread_price_usd | O1: transport_oneway_usd | P1: transport_monthly_pass_usd | Q1: rent_monthly_usd | R1: utilities_monthly_usd | S1: data_completeness | T1: expansion_affordability_score | U1: rank_key
A2: Afghanistan | B2: Middle East, North Africa, Afghanistan & Pakistan | C2: Low income | D2: Kabul | E2: 34.5228 | F2: 69.1761 | G2: 2024 | H2: -6.6 | I2: 38.2 | J2: 8.2 | K2: 36.8 | L2: 36.9 | M2: 48.5 | N2: 0.88 | O2: 1.05 | P2: 12.8 | Q2: 85 | R2: 20 | S2: Full data | T2: 69.4 | U2: =T2+(ROW()-2)*0.0000001 -> 69.4
A3: Albania | B3: Europe & Central Asia | C3: Upper middle income | D3: Tirane | E3: 41.3317 | F3: 19.8172 | G3: 2024 | H3: 2.22 | S3: Inflation only | T3: 56.8 | U3: =T3+(ROW()-2)*0.0000001 -> 56.8
A4: Algeria | B4: Middle East, North Africa, Afghanistan & Pakistan | C4: Upper middle income | D4: Algiers | E4: 36.7397 | F4: 3.05097 | G4: 2024 | H4: 4.05 | S4: Inflation only | T4: 56.3 | U4: =T4+(ROW()-2)*0.0000001 -> 56.3
A5: American Samoa | B5: East Asia & Pacific | C5: High income | D5: Pago Pago | E5: -14.2846 | F5: -170.691 | S5: Reference only | T5: 54.5 | U5: =T5+(ROW()-2)*0.0000001 -> 54.5
A6: Andorra | B6: Europe & Central Asia | C6: High income | D6: Andorra la Vella | E6: 42.5075 | F6: 1.5218 | S6: Reference only | T6: 54.5 | U6: =T6+(ROW()-2)*0.0000001 -> 54.5
A7: Angola | B7: Sub-Saharan Africa | C7: Lower middle income | D7: Luanda | E7: -8.81155 | F7: 13.242 | G7: 2024 | H7: 28.24 | S7: Inflation only | T7: 49 | U7: =T7+(ROW()-2)*0.0000001 -> 49
A8: Antigua and Barbuda | B8: Latin America & Caribbean | C8: High income | D8: Saint John's | E8: 17.1175 | F8: -61.8456 | G8: 2024 | H8: 6.2 | S8: Inflation only | T8: 55.6 | U8: =T8+(ROW()-2)*0.0000001 -> 55.600001
A9: Argentina | B9: Latin America & Caribbean | C9: Upper middle income | D9: Buenos Aires | E9: -34.6118 | F9: -58.4173 | G9: 2024 | H9: 219.88 | S9: Inflation only | T9: 42.5 | U9: =T9+(ROW()-2)*0.0000001 -> 42.500001
A10: Armenia | B10: Europe & Central Asia | C10: Upper middle income | D10: Yerevan | E10: 40.1596 | F10: 44.509 | G10: 2024 | H10: 0.27 | S10: Inflation only | T10: 57.4 | U10: =T10+(ROW()-2)*0.0000001 -> 57.400001
A11: Aruba | B11: Latin America & Caribbean | C11: High income | D11: Oranjestad | E11: 12.5167 | F11: -70.0167 | S11: Reference only | T11: 54.5 | U11: =T11+(ROW()-2)*0.0000001 -> 54.500001
A12: Australia | B12: East Asia & Pacific | C12: High income | D12: Canberra | E12: -35.282 | F12: 149.129 | G12: 2024 | H12: 3.17 | I12: 69.5 | J12: 32.8 | K12: 65.4 | L12: 68.9 | M12: 95.6 | N12: 3.25 | Q12: 1450 | R12: 140 | S12: Full data | T12: 68.3 | U12: =T12+(ROW()-2)*0.0000001 -> 68.300001
A13: Austria | B13: Europe & Central Asia | C13: High income | D13: Vienna | E13: 48.2201 | F13: 16.3798 | G13: 2024 | H13: 2.94 | S13: Inflation only | T13: 56.6 | U13: =T13+(ROW()-2)*0.0000001 -> 56.600001
A14: Azerbaijan | B14: Europe & Central Asia | C14: Upper middle income | D14: Baku | E14: 40.3834 | F14: 49.8932 | G14: 2024 | H14: 2.21 | S14: Inflation only | T14: 56.8 | U14: =T14+(ROW()-2)*0.0000001 -> 56.800001
A15: Bahamas, The | B15: Latin America & Caribbean | C15: High income | D15: Nassau | E15: 25.0661 | F15: -77.339 | G15: 2024 | H15: 0.41 | S15: Inflation only | T15: 57.4 | U15: =T15+(ROW()-2)*0.0000001 -> 57.400001
A16: Bahrain | B16: Middle East, North Africa, Afghanistan & Pakistan | C16: High income | D16: Manama | E16: 26.1921 | F16: 50.5354 | G16: 2024 | H16: 0.92 | I16: 65.2 | J16: 26.1 | K16: 61.8 | L16: 63.5 | M16: 86.2 | Q16: 600 | S16: Full data | T16: 68.2 | U16: =T16+(ROW()-2)*0.0000001 -> 68.200001
A17: Bangladesh | B17: South Asia | C17: Lower middle income | D17: Dhaka | E17: 23.7055 | F17: 90.4113 | G17: 2024 | H17: 10.47 | I17: 39.5 | J17: 8.8 | K17: 38.1 | L17: 38.2 | M17: 50.8 | N17: 0.95 | O17: 1.18 | P17: 14.5 | Q17: 100 | R17: 25 | S17: Full data | T17: 64.5 | U17: =T17+(ROW()-2)*0.0000001 -> 64.500001
A18: Barbados | B18: Latin America & Caribbean | C18: High income | D18: Bridgetown | E18: 13.0935 | F18: -59.6105 | G18: 2024 | H18: 1.45 | I18: 75.2 | J18: 41.8 | K18: 70.8 | L18: 73.2 | M18: 88.5 | Q18: 1200 | S18: Full data | T18: 62.9 | U18: =T18+(ROW()-2)*0.0000001 -> 62.900002
A19: Belarus | B19: Europe & Central Asia | C19: Upper middle income | D19: Minsk | E19: 53.9678 | F19: 27.5766 | G19: 2024 | H19: 5.79 | S19: Inflation only | T19: 55.8 | U19: =T19+(ROW()-2)*0.0000001 -> 55.800002
A20: Belgium | B20: Europe & Central Asia | C20: High income | D20: Brussels | E20: 50.8371 | F20: 4.36761 | G20: 2024 | H20: 3.14 | S20: Inflation only | T20: 56.6 | U20: =T20+(ROW()-2)*0.0000001 -> 56.600002
A21: Belize | B21: Latin America & Caribbean | C21: Upper middle income | D21: Belmopan | E21: 17.2534 | F21: -88.7713 | G21: 2024 | H21: 3.29 | S21: Inflation only | T21: 56.5 | U21: =T21+(ROW()-2)*0.0000001 -> 56.500002
A22: Benin | B22: Sub-Saharan Africa | C22: Lower middle income | D22: Porto-Novo | E22: 6.4779 | F22: 2.6323 | G22: 2024 | H22: 1.16 | S22: Inflation only | T22: 57.2 | U22: =T22+(ROW()-2)*0.0000001 -> 57.200002
A23: Bermuda | B23: North America | C23: High income | D23: Hamilton | E23: 32.3293 | F23: -64.706 | S23: Reference only | T23: 54.5 | U23: =T23+(ROW()-2)*0.0000001 -> 54.500002
A24: Bhutan | B24: South Asia | C24: Lower middle income | D24: Thimphu | E24: 27.5768 | F24: 89.6177 | G24: 2024 | H24: 2.76 | S24: Inflation only | T24: 56.7 | U24: =T24+(ROW()-2)*0.0000001 -> 56.700002
A25: Bolivia | B25: Latin America & Caribbean | C25: Lower middle income | D25: La Paz | E25: -13.9908 | F25: -66.1936 | G25: 2024 | H25: 5.1 | S25: Inflation only | T25: 56 | U25: =T25+(ROW()-2)*0.0000001 -> 56.000002
A26: Bosnia and Herzegovina | B26: Europe & Central Asia | C26: Upper middle income | D26: Sarajevo | E26: 43.8607 | F26: 18.4214 | G26: 2023 | H26: 6.11 | S26: Inflation only | T26: 55.7 | U26: =T26+(ROW()-2)*0.0000001 -> 55.700002
A27: Botswana | B27: Sub-Saharan Africa | C27: Upper middle income | D27: Gaborone | E27: -24.6544 | F27: 25.9201 | G27: 2024 | H27: 2.82 | S27: Inflation only | T27: 56.7 | U27: =T27+(ROW()-2)*0.0000001 -> 56.700002
A28: Brazil | B28: Latin America & Caribbean | C28: Upper middle income | D28: Brasilia | E28: -15.7801 | F28: -47.9292 | G28: 2024 | H28: 4.37 | I28: 51.4 | J28: 15.9 | K28: 49.2 | L28: 50.1 | M28: 67.5 | N28: 1.85 | O28: 2.85 | P28: 52.4 | Q28: 270 | R28: 70 | S28: Full data | T28: 66.9 | U28: =T28+(ROW()-2)*0.0000001 -> 66.900003
A29: British Virgin Islands | B29: Latin America & Caribbean | C29: High income | D29: Road Town | E29: 18.431389 | F29: -64.623056 | S29: Reference only | T29: 54.5 | U29: =T29+(ROW()-2)*0.0000001 -> 54.500003
A30: Brunei Darussalam | B30: East Asia & Pacific | C30: High income | D30: Bandar Seri Begawan | E30: 4.94199 | F30: 114.946 | G30: 2024 | H30: -0.39 | S30: Inflation only | T30: 57.6 | U30: =T30+(ROW()-2)*0.0000001 -> 57.600003
A31: Bulgaria | B31: Europe & Central Asia | C31: High income | D31: Sofia | E31: 42.7105 | F31: 23.3238 | G31: 2024 | H31: 2.45 | S31: Inflation only | T31: 56.8 | U31: =T31+(ROW()-2)*0.0000001 -> 56.800003
A32: Burkina Faso | B32: Sub-Saharan Africa | C32: Low income | D32: Ouagadougou | E32: 12.3605 | F32: -1.53395 | G32: 2024 | H32: 4.19 | S32: Inflation only | T32: 56.2 | U32: =T32+(ROW()-2)*0.0000001 -> 56.200003
A33: Burundi | B33: Sub-Saharan Africa | C33: Low income | D33: Bujumbura | E33: -3.3784 | F33: 29.3639 | G33: 2024 | H33: 20.21 | S33: Inflation only | T33: 51.4 | U33: =T33+(ROW()-2)*0.0000001 -> 51.400003
A34: Cabo Verde | B34: Sub-Saharan Africa | C34: Upper middle income | D34: Praia | E34: 14.9218 | F34: -23.5087 | G34: 2024 | H34: 1.05 | S34: Inflation only | T34: 57.2 | U34: =T34+(ROW()-2)*0.0000001 -> 57.200003
A35: Cambodia | B35: East Asia & Pacific | C35: Lower middle income | D35: Phnom Penh | E35: 11.5556 | F35: 104.874 | G35: 2024 | H35: 0.81 | I35: 50.2 | J35: 14.5 | K35: 48.2 | L35: 48.5 | M35: 65.2 | Q35: 160 | S35: Full data | T35: 67.8 | U35: =T35+(ROW()-2)*0.0000001 -> 67.800003
A36: Cameroon | B36: Sub-Saharan Africa | C36: Lower middle income | D36: Yaounde | E36: 3.8721 | F36: 11.5174 | G36: 2024 | H36: 4.53 | S36: Inflation only | T36: 56.1 | U36: =T36+(ROW()-2)*0.0000001 -> 56.100003
A37: Canada | B37: North America | C37: High income | D37: Ottawa | E37: 45.4215 | F37: -75.6919 | G37: 2024 | H37: 2.38 | I37: 65.4 | J37: 28.4 | K37: 61.5 | L37: 64.2 | M37: 92.1 | N37: 3.18 | Q37: 1200 | R37: 145 | S37: Full data | T37: 69.4 | U37: =T37+(ROW()-2)*0.0000001 -> 69.400003
A38: Cayman Islands | B38: Latin America & Caribbean | C38: High income | D38: George Town | E38: 19.3022 | F38: -81.3857 | I38: 94.3 | J38: 60.2 | K38: 85.6 | L38: 92.1 | M38: 115.8 | N38: 6.36 | Q38: 2500 | S38: Cost data only | T38: 60.5 | U38: =T38+(ROW()-2)*0.0000001 -> 60.500004
A39: Central African Republic | B39: Sub-Saharan Africa | C39: Low income | D39: Bangui | E39: 5.63056 | F39: 21.6407 | G39: 2024 | H39: 1.48 | S39: Inflation only | T39: 57.1 | U39: =T39+(ROW()-2)*0.0000001 -> 57.100004
A40: Chad | B40: Sub-Saharan Africa | C40: Low income | D40: N'Djamena | E40: 12.1048 | F40: 15.0445 | G40: 2024 | H40: 8.9 | S40: Inflation only | T40: 54.8 | U40: =T40+(ROW()-2)*0.0000001 -> 54.800004
A41: Channel Islands | B41: Europe & Central Asia | C41: High income | S41: Reference only | T41: 54.5 | U41: =T41+(ROW()-2)*0.0000001 -> 54.500004
A42: Chile | B42: Latin America & Caribbean | C42: High income | D42: Santiago | E42: -33.475 | F42: -70.6475 | G42: 2024 | H42: 4.3 | S42: Inflation only | T42: 56.2 | U42: =T42+(ROW()-2)*0.0000001 -> 56.200004
A43: China | B43: East Asia & Pacific | C43: Upper middle income | D43: Beijing | E43: 40.0495 | F43: 116.286 | G43: 2024 | H43: 0.22 | I43: 49.8 | J43: 14.8 | K43: 47.8 | L43: 48.5 | M43: 64.2 | N43: 1.65 | O43: 2.45 | P43: 42.8 | Q43: 540 | R43: 80 | S43: Full data | T43: 67.8 | U43: =T43+(ROW()-2)*0.0000001 -> 67.800004
A44: Colombia | B44: Latin America & Caribbean | C44: Upper middle income | D44: Bogota | E44: 4.60987 | F44: -74.082 | G44: 2024 | H44: 6.61 | S44: Inflation only | T44: 55.5 | U44: =T44+(ROW()-2)*0.0000001 -> 55.500004
A45: Comoros | B45: Sub-Saharan Africa | C45: Lower middle income | D45: Moroni | E45: -11.6986 | F45: 43.2418 | G45: 2024 | H45: 5.05 | S45: Inflation only | T45: 56 | U45: =T45+(ROW()-2)*0.0000001 -> 56.000004
A46: Congo, Dem. Rep. | B46: Sub-Saharan Africa | C46: Low income | D46: Kinshasa | E46: -4.325 | F46: 15.3222 | S46: Reference only | T46: 54.5 | U46: =T46+(ROW()-2)*0.0000001 -> 54.500004
A47: Congo, Rep. | B47: Sub-Saharan Africa | C47: Lower middle income | D47: Brazzaville | E47: -4.2767 | F47: 15.2662 | G47: 2024 | H47: 3.09 | S47: Inflation only | T47: 56.6 | U47: =T47+(ROW()-2)*0.0000001 -> 56.600004
A48: Costa Rica | B48: Latin America & Caribbean | C48: High income | D48: San Jose | E48: 9.63701 | F48: -84.0089 | G48: 2024 | H48: -0.41 | S48: Inflation only | T48: 57.6 | U48: =T48+(ROW()-2)*0.0000001 -> 57.600005
A49: Cote d'Ivoire | B49: Sub-Saharan Africa | C49: Lower middle income | D49: Yamoussoukro | E49: 5.332 | F49: -4.0305 | G49: 2024 | H49: 3.45 | S49: Inflation only | T49: 56.5 | U49: =T49+(ROW()-2)*0.0000001 -> 56.500005
A50: Croatia | B50: Europe & Central Asia | C50: High income | D50: Zagreb | E50: 45.8069 | F50: 15.9614 | G50: 2024 | H50: 2.97 | S50: Inflation only | T50: 56.6 | U50: =T50+(ROW()-2)*0.0000001 -> 56.600005
A51: Cuba | B51: Latin America & Caribbean | C51: Upper middle income | D51: Havana | E51: 23.1333 | F51: -82.3667 | S51: Reference only | T51: 54.5 | U51: =T51+(ROW()-2)*0.0000001 -> 54.500005
A52: Curacao | B52: Latin America & Caribbean | C52: High income | D52: Willemstad | S52: Reference only | T52: 54.5 | U52: =T52+(ROW()-2)*0.0000001 -> 54.500005
A53: Cyprus | B53: Europe & Central Asia | C53: High income | D53: Nicosia | E53: 35.1676 | F53: 33.3736 | G53: 2024 | H53: 1.8 | S53: Inflation only | T53: 57 | U53: =T53+(ROW()-2)*0.0000001 -> 57.000005
A54: Czechia | B54: Europe & Central Asia | C54: High income | D54: Prague | E54: 50.0878 | F54: 14.4205 | G54: 2024 | H54: 2.44 | S54: Inflation only | T54: 56.8 | U54: =T54+(ROW()-2)*0.0000001 -> 56.800005
A55: Denmark | B55: Europe & Central Asia | C55: High income | D55: Copenhagen | E55: 55.6763 | F55: 12.5681 | G55: 2024 | H55: 1.37 | I55: 72.1 | J55: 36.4 | K55: 67.2 | L55: 75.3 | M55: 102.8 | N55: 3.48 | O55: 5.42 | P55: 128.5 | S55: Full data | T55: 69.9 | U55: =T55+(ROW()-2)*0.0000001 -> 69.900005
A56: Djibouti | B56: Middle East, North Africa, Afghanistan & Pakistan | C56: Lower middle income | D56: Djibouti | E56: 11.5806 | F56: 43.1425 | G56: 2024 | H56: 2.11 | S56: Inflation only | T56: 56.9 | U56: =T56+(ROW()-2)*0.0000001 -> 56.900005
A57: Dominica | B57: Latin America & Caribbean | C57: Upper middle income | D57: Roseau | E57: 15.2976 | F57: -61.39 | G57: 2024 | H57: 2.74 | S57: Inflation only | T57: 56.7 | U57: =T57+(ROW()-2)*0.0000001 -> 56.700006
A58: Dominican Republic | B58: Latin America & Caribbean | C58: Upper middle income | D58: Santo Domingo | E58: 18.479 | F58: -69.8908 | G58: 2024 | H58: 3.3 | S58: Inflation only | T58: 56.5 | U58: =T58+(ROW()-2)*0.0000001 -> 56.500006
A59: Ecuador | B59: Latin America & Caribbean | C59: Upper middle income | D59: Quito | E59: -0.229498 | F59: -78.5243 | G59: 2024 | H59: 1.55 | S59: Inflation only | T59: 57 | U59: =T59+(ROW()-2)*0.0000001 -> 57.000006
A60: Egypt, Arab Rep. | B60: Middle East, North Africa, Afghanistan & Pakistan | C60: Lower middle income | D60: Cairo | E60: 30.0982 | F60: 31.2461 | G60: 2024 | H60: 28.27 | S60: Inflation only | T60: 49 | U60: =T60+(ROW()-2)*0.0000001 -> 49.000006
A61: El Salvador | B61: Latin America & Caribbean | C61: Upper middle income | D61: San Salvador | E61: 13.7034 | F61: -89.2073 | G61: 2024 | H61: 0.85 | S61: Inflation only | T61: 57.2 | U61: =T61+(ROW()-2)*0.0000001 -> 57.200006
A62: Equatorial Guinea | B62: Sub-Saharan Africa | C62: Upper middle income | D62: Malabo | E62: 3.7523 | F62: 8.7741 | G62: 2024 | H62: 2.92 | S62: Inflation only | T62: 56.6 | U62: =T62+(ROW()-2)*0.0000001 -> 56.600006
A63: Eritrea | B63: Sub-Saharan Africa | C63: Low income | D63: Asmara | E63: 15.3315 | F63: 38.9183 | S63: Reference only | T63: 54.5 | U63: =T63+(ROW()-2)*0.0000001 -> 54.500006
A64: Estonia | B64: Europe & Central Asia | C64: High income | D64: Tallinn | E64: 59.4392 | F64: 24.7586 | G64: 2024 | H64: 3.52 | S64: Inflation only | T64: 56.4 | U64: =T64+(ROW()-2)*0.0000001 -> 56.400006
A65: Eswatini | B65: Sub-Saharan Africa | C65: Lower middle income | D65: Mbabane | E65: -26.5225 | F65: 31.4659 | S65: Reference only | T65: 54.5 | U65: =T65+(ROW()-2)*0.0000001 -> 54.500006
A66: Ethiopia | B66: Sub-Saharan Africa | C66: Low income | D66: Addis Ababa | E66: 9.02274 | F66: 38.7468 | G66: 2024 | H66: 21.04 | S66: Inflation only | T66: 51.2 | U66: =T66+(ROW()-2)*0.0000001 -> 51.200006
A67: Faroe Islands | B67: Europe & Central Asia | C67: High income | D67: Torshavn | E67: 61.8926 | F67: -6.91181 | S67: Reference only | T67: 54.5 | U67: =T67+(ROW()-2)*0.0000001 -> 54.500006
A68: Fiji | B68: East Asia & Pacific | C68: Upper middle income | D68: Suva | E68: -18.1149 | F68: 178.399 | G68: 2024 | H68: 3.89 | S68: Inflation only | T68: 56.3 | U68: =T68+(ROW()-2)*0.0000001 -> 56.300007
A69: Finland | B69: Europe & Central Asia | C69: High income | D69: Helsinki | E69: 60.1608 | F69: 24.9525 | G69: 2024 | H69: 1.57 | S69: Inflation only | T69: 57 | U69: =T69+(ROW()-2)*0.0000001 -> 57.000007
A70: France | B70: Europe & Central Asia | C70: High income | D70: Paris | E70: 48.8566 | F70: 2.35097 | G70: 2024 | H70: 2 | I70: 64.8 | J70: 27.9 | K70: 60.8 | L70: 63.5 | M70: 89.7 | N70: 2.78 | O70: 4.62 | P70: 108.4 | Q70: 738 | R70: 155 | S70: Full data | T70: 68.9 | U70: =T70+(ROW()-2)*0.0000001 -> 68.900007
A71: French Polynesia | B71: East Asia & Pacific | C71: High income | D71: Papeete | E71: -17.535 | F71: -149.57 | S71: Reference only | T71: 54.5 | U71: =T71+(ROW()-2)*0.0000001 -> 54.500007
A72: Gabon | B72: Sub-Saharan Africa | C72: Upper middle income | D72: Libreville | E72: 0.38832 | F72: 9.45162 | G72: 2024 | H72: 1.17 | S72: Inflation only | T72: 57.1 | U72: =T72+(ROW()-2)*0.0000001 -> 57.100007
A73: Gambia, The | B73: Sub-Saharan Africa | C73: Low income | D73: Banjul | E73: 13.4495 | F73: -16.5885 | G73: 2024 | H73: 11.56 | S73: Inflation only | T73: 54 | U73: =T73+(ROW()-2)*0.0000001 -> 54.000007
A74: Georgia | B74: Europe & Central Asia | C74: Upper middle income | D74: Tbilisi | E74: 41.71 | F74: 44.793 | G74: 2024 | H74: 1.11 | S74: Inflation only | T74: 57.2 | U74: =T74+(ROW()-2)*0.0000001 -> 57.200007
A75: Germany | B75: Europe & Central Asia | C75: High income | D75: Berlin | E75: 52.5235 | F75: 13.4115 | G75: 2024 | H75: 2.26 | I75: 64.1 | J75: 26.5 | K75: 59.7 | L75: 62.8 | M75: 91.3 | N75: 2.72 | O75: 4.85 | P75: 112.3 | Q75: 850 | R75: 170 | S75: Full data | T75: 69.9 | U75: =T75+(ROW()-2)*0.0000001 -> 69.900007
A76: Ghana | B76: Sub-Saharan Africa | C76: Lower middle income | D76: Accra | E76: 5.57045 | F76: -0.20795 | G76: 2024 | H76: 22.85 | S76: Inflation only | T76: 50.6 | U76: =T76+(ROW()-2)*0.0000001 -> 50.600007
A77: Gibraltar | B77: Europe & Central Asia | C77: High income | S77: Reference only | T77: 54.5 | U77: =T77+(ROW()-2)*0.0000001 -> 54.500008
A78: Greece | B78: Europe & Central Asia | C78: High income | D78: Athens | E78: 37.9792 | F78: 23.7166 | G78: 2024 | H78: 2.74 | I78: 57.1 | J78: 19.2 | K78: 53.8 | L78: 55.1 | M78: 76.4 | N78: 2.38 | O78: 3.62 | P78: 78.2 | Q78: 380 | R78: 75 | S78: Full data | T78: 68.1 | U78: =T78+(ROW()-2)*0.0000001 -> 68.100008
A79: Greenland | B79: Europe & Central Asia | C79: High income | D79: Nuuk | E79: 64.1836 | F79: -51.7214 | S79: Reference only | T79: 54.5 | U79: =T79+(ROW()-2)*0.0000001 -> 54.500008
A80: Grenada | B80: Latin America & Caribbean | C80: Upper middle income | D80: Saint George's | E80: 12.0653 | F80: -61.7449 | G80: 2024 | H80: 1.09 | S80: Inflation only | T80: 57.2 | U80: =T80+(ROW()-2)*0.0000001 -> 57.200008
A81: Guam | B81: East Asia & Pacific | C81: High income | D81: Agana | E81: 13.4443 | F81: 144.794 | S81: Reference only | T81: 54.5 | U81: =T81+(ROW()-2)*0.0000001 -> 54.500008
A82: Guatemala | B82: Latin America & Caribbean | C82: Upper middle income | D82: Guatemala City | E82: 14.6248 | F82: -90.5328 | G82: 2024 | H82: 2.87 | S82: Inflation only | T82: 56.6 | U82: =T82+(ROW()-2)*0.0000001 -> 56.600008
A83: Guinea | B83: Sub-Saharan Africa | C83: Lower middle income | D83: Conakry | E83: 9.51667 | F83: -13.7 | G83: 2024 | H83: 8.12 | S83: Inflation only | T83: 55.1 | U83: =T83+(ROW()-2)*0.0000001 -> 55.100008
A84: Guinea-Bissau | B84: Sub-Saharan Africa | C84: Low income | D84: Bissau | E84: 11.8037 | F84: -15.1804 | G84: 2024 | H84: 3.77 | S84: Inflation only | T84: 56.4 | U84: =T84+(ROW()-2)*0.0000001 -> 56.400008
A85: Guyana | B85: Latin America & Caribbean | C85: High income | D85: Georgetown | E85: 6.80461 | F85: -58.1548 | G85: 2024 | H85: 2.9 | S85: Inflation only | T85: 56.6 | U85: =T85+(ROW()-2)*0.0000001 -> 56.600008
A86: Haiti | B86: Latin America & Caribbean | C86: Lower middle income | D86: Port-au-Prince | E86: 18.5392 | F86: -72.3288 | G86: 2024 | H86: 26.95 | S86: Inflation only | T86: 49.4 | U86: =T86+(ROW()-2)*0.0000001 -> 49.400008
A87: Honduras | B87: Latin America & Caribbean | C87: Lower middle income | D87: Tegucigalpa | E87: 15.1333 | F87: -87.4667 | G87: 2024 | H87: 4.61 | S87: Inflation only | T87: 56.1 | U87: =T87+(ROW()-2)*0.0000001 -> 56.100009
A88: Hong Kong SAR, China | B88: East Asia & Pacific | C88: High income | E88: 22.3964 | F88: 114.109 | G88: 2024 | H88: 1.73 | S88: Inflation only | T88: 57 | U88: =T88+(ROW()-2)*0.0000001 -> 57.000009
A89: Hungary | B89: Europe & Central Asia | C89: High income | D89: Budapest | E89: 47.4984 | F89: 19.0408 | G89: 2024 | H89: 3.7 | S89: Inflation only | T89: 56.4 | U89: =T89+(ROW()-2)*0.0000001 -> 56.400009
A90: Iceland | B90: Europe & Central Asia | C90: High income | D90: Reykjavik | E90: 64.1353 | F90: -21.8952 | G90: 2024 | H90: 5.86 | I90: 78.2 | J90: 45.6 | K90: 72.3 | L90: 82.1 | M90: 98.7 | N90: 4.26 | O90: 7.94 | P90: 131.85 | S90: Full data | T90: 63.6 | U90: =T90+(ROW()-2)*0.0000001 -> 63.600009
A91: India | B91: South Asia | C91: Lower middle income | D91: New Delhi | E91: 28.6353 | F91: 77.225 | G91: 2024 | H91: 4.95 | I91: 48.5 | J91: 13.5 | K91: 46.2 | L91: 47.1 | M91: 62.5 | N91: 1.52 | O91: 2.18 | P91: 35.2 | Q91: 164 | R91: 45 | S91: Full data | T91: 66.4 | U91: =T91+(ROW()-2)*0.0000001 -> 66.400009
A92: Indonesia | B92: East Asia & Pacific | C92: Upper middle income | D92: Jakarta | E92: -6.19752 | F92: 106.83 | G92: 2024 | H92: 2.18 | I92: 47.2 | J92: 12.8 | K92: 45.1 | L92: 45.8 | M92: 60.8 | N92: 1.45 | O92: 2.05 | P92: 32.4 | Q92: 305 | R92: 55 | S92: Full data | T92: 67.2 | U92: =T92+(ROW()-2)*0.0000001 -> 67.200009
A93: Iran, Islamic Rep. | B93: Middle East, North Africa, Afghanistan & Pakistan | C93: Upper middle income | D93: Tehran | E93: 35.6878 | F93: 51.4447 | G93: 2024 | H93: 32.46 | S93: Inflation only | T93: 47.8 | U93: =T93+(ROW()-2)*0.0000001 -> 47.800009
A94: Iraq | B94: Middle East, North Africa, Afghanistan & Pakistan | C94: Upper middle income | D94: Baghdad | E94: 33.3302 | F94: 44.394 | G94: 2024 | H94: 2.61 | S94: Inflation only | T94: 56.7 | U94: =T94+(ROW()-2)*0.0000001 -> 56.700009
A95: Ireland | B95: Europe & Central Asia | C95: High income | D95: Dublin | E95: 53.3441 | F95: -6.26749 | G95: 2024 | H95: 2.11 | I95: 68.9 | J95: 40.2 | K95: 64.7 | L95: 70.1 | M95: 92.4 | S95: Full data | T95: 66.6 | U95: =T95+(ROW()-2)*0.0000001 -> 66.600009
A96: Isle of Man | B96: Europe & Central Asia | C96: High income | D96: Douglas | E96: 54.1509 | F96: -4.47928 | S96: Reference only | T96: 54.5 | U96: =T96+(ROW()-2)*0.0000001 -> 54.500009
A97: Israel | B97: Middle East, North Africa, Afghanistan & Pakistan | C97: High income | E97: 31.7717 | F97: 35.2035 | G97: 2024 | H97: 3.07 | S97: Inflation only | T97: 56.6 | U97: =T97+(ROW()-2)*0.0000001 -> 56.600009
A98: Italy | B98: Europe & Central Asia | C98: High income | D98: Rome | E98: 41.8955 | F98: 12.4823 | G98: 2024 | H98: 0.98 | I98: 62.5 | J98: 23.7 | K98: 58.2 | L98: 60.5 | M98: 83.6 | N98: 2.65 | O98: 4.25 | P98: 98.5 | Q98: 550 | R98: 110 | S98: Full data | T98: 68.5 | U98: =T98+(ROW()-2)*0.0000001 -> 68.50001
A99: Jamaica | B99: Latin America & Caribbean | C99: Upper middle income | D99: Kingston | E99: 17.9927 | F99: -76.792 | G99: 2024 | H99: 5.41 | S99: Inflation only | T99: 55.9 | U99: =T99+(ROW()-2)*0.0000001 -> 55.90001
A100: Japan | B100: East Asia & Pacific | C100: High income | D100: Tokyo | E100: 35.67 | F100: 139.77 | G100: 2024 | H100: 2.74 | I100: 63.2 | J100: 24.8 | K100: 58.9 | L100: 61.2 | M100: 85.4 | N100: 2.85 | Q100: 750 | R100: 130 | S100: Full data | T100: 68.2 | U100: =T100+(ROW()-2)*0.0000001 -> 68.20001
...

Sheet Regional_Summary
A1: Regional Cost-of-Living Summary
A2: All figures computed live via AVERAGEIFS/COUNTIFS against Clean_Data
A4: Region | B4: Countries Reporting Cost Data | C4: Avg Cost of Living Index | D4: Avg Rent (USD/mo) | E4: Avg Purchasing Power Index | F4: Avg Inflation %
A5: East Asia & Pacific | B5: =COUNTIFS(Clean_Data!B2:B218,A5,Clean_Data!I2:I218,"<>") -> 12 | C5: =IFERROR(ROUND(AVERAGEIFS(Clean_Data!I2:I218,Clean_Data!B2:B218,A5),1),"n/a") -> 56.8 | D5: =IFERROR(ROUND(AVERAGEIFS(Clean_Data!Q2:Q218,Clean_Data!B2:B218,A5),0),"n/a") -> 752 | E5: =IFERROR(ROUND(AVERAGEIFS(Clean_Data!M2:M218,Clean_Data!B2:B218,A5),1),"n/a") -> 73.8 | F5: =IFERROR(ROUND(AVERAGEIFS(Clean_Data!H2:H218,Clean_Data!B2:B218,A5),2),"n/a") -> 3.13
A6: Europe & Central Asia | B6: =COUNTIFS(Clean_Data!B2:B218,A6,Clean_Data!I2:I218,"<>") -> 13 | C6: =IFERROR(ROUND(AVERAGEIFS(Clean_Data!I2:I218,Clean_Data!B2:B218,A6),1),"n/a") -> 66.6 | D6: =IFERROR(ROUND(AVERAGEIFS(Clean_Data!Q2:Q218,Clean_Data!B2:B218,A6),0),"n/a") -> 773 | E6: =IFERROR(ROUND(AVERAGEIFS(Clean_Data!M2:M218,Clean_Data!B2:B218,A6),1),"n/a") -> 91.2 | F6: =IFERROR(ROUND(AVERAGEIFS(Clean_Data!H2:H218,Clean_Data!B2:B218,A6),2),"n/a") -> 4.43
A7: Latin America & Caribbean | B7: =COUNTIFS(Clean_Data!B2:B218,A7,Clean_Data!I2:I218,"<>") -> 4 | C7: =IFERROR(ROUND(AVERAGEIFS(Clean_Data!I2:I218,Clean_Data!B2:B218,A7),1),"n/a") -> 68.4 | D7: =IFERROR(ROUND(AVERAGEIFS(Clean_Data!Q2:Q218,Clean_Data!B2:B218,A7),0),"n/a") -> 1080 | E7: =IFERROR(ROUND(AVERAGEIFS(Clean_Data!M2:M218,Clean_Data!B2:B218,A7),1),"n/a") -> 85.4 | F7: =IFERROR(ROUND(AVERAGEIFS(Clean_Data!H2:H218,Clean_Data!B2:B218,A7),2),"n/a") -> 11.21
A8: Middle East, North Africa, Afghanistan & Pakistan | B8: =COUNTIFS(Clean_Data!B2:B218,A8,Clean_Data!I2:I218,"<>") -> 8 | C8: =IFERROR(ROUND(AVERAGEIFS(Clean_Data!I2:I218,Clean_Data!B2:B218,A8),1),"n/a") -> 61.3 | D8: =IFERROR(ROUND(AVERAGEIFS(Clean_Data!Q2:Q218,Clean_Data!B2:B218,A8),0),"n/a") -> 598 | E8: =IFERROR(ROUND(AVERAGEIFS(Clean_Data!M2:M218,Clean_Data!B2:B218,A8),1),"n/a") -> 80.3 | F8: =IFERROR(ROUND(AVERAGEIFS(Clean_Data!H2:H218,Clean_Data!B2:B218,A8),2),"n/a") -> 9.53
A9: North America | B9: =COUNTIFS(Clean_Data!B2:B218,A9,Clean_Data!I2:I218,"<>") -> 2 | C9: =IFERROR(ROUND(AVERAGEIFS(Clean_Data!I2:I218,Clean_Data!B2:B218,A9),1),"n/a") -> 69.9 | D9: =IFERROR(ROUND(AVERAGEIFS(Clean_Data!Q2:Q218,Clean_Data!B2:B218,A9),0),"n/a") -> 1402 | E9: =IFERROR(ROUND(AVERAGEIFS(Clean_Data!M2:M218,Clean_Data!B2:B218,A9),1),"n/a") -> 96.1 | F9: =IFERROR(ROUND(AVERAGEIFS(Clean_Data!H2:H218,Clean_Data!B2:B218,A9),2),"n/a") -> 2.67
A10: South Asia | B10: =COUNTIFS(Clean_Data!B2:B218,A10,Clean_Data!I2:I218,"<>") -> 4 | C10: =IFERROR(ROUND(AVERAGEIFS(Clean_Data!I2:I218,Clean_Data!B2:B218,A10),1),"n/a") -> 48.3 | D10: =IFERROR(ROUND(AVERAGEIFS(Clean_Data!Q2:Q218,Clean_Data!B2:B218,A10),0),"n/a") -> 154 | E10: =IFERROR(ROUND(AVERAGEIFS(Clean_Data!M2:M218,Clean_Data!B2:B218,A10),1),"n/a") -> 62.8 | F10: =IFERROR(ROUND(AVERAGEIFS(Clean_Data!H2:H218,Clean_Data!B2:B218,A10),2),"n/a") -> 3.98
A11: Sub-Saharan Africa | B11: =COUNTIFS(Clean_Data!B2:B218,A11,Clean_Data!I2:I218,"<>") -> 2 | C11: =IFERROR(ROUND(AVERAGEIFS(Clean_Data!I2:I218,Clean_Data!B2:B218,A11),1),"n/a") -> 45.5 | D11: =IFERROR(ROUND(AVERAGEIFS(Clean_Data!Q2:Q218,Clean_Data!B2:B218,A11),0),"n/a") -> 250 | E11: =IFERROR(ROUND(AVERAGEIFS(Clean_Data!M2:M218,Clean_Data!B2:B218,A11),1),"n/a") -> 59.2 | F11: =IFERROR(ROUND(AVERAGEIFS(Clean_Data!H2:H218,Clean_Data!B2:B218,A11),2),"n/a") -> 15.54

Sheet Dashboard
B2: Global Market Expansion & Cost-of-Living Intelligence
B3: Source: Kaggle — World Bank inflation data + cost-of-living index mashup (217 countries)
B6: Total Countries (Reference) | D6: =COUNTA(Clean_Data!A2:A218) -> 217
B7: Countries with Full Cost Data | D7: =COUNTIF(Clean_Data!S2:S218,"Full data") -> 43
B8: Countries with Inflation Data Only | D8: =COUNTIF(Clean_Data!S2:S218,"Inflation only") -> 136
B9: Highest Inflation (Risk Flag) | D9: =INDEX(Clean_Data!A2:A218,MATCH(MAX(Clean_Data!H2:H218),Clean_Data!H2:H218,0)) -> Argentina
B10: Most Affordable (Full Data, by Score) | D10: =INDEX(Clean_Data!A2:A218,MATCH(MAX(Clean_Data!T2:T218),Clean_Data!T2:T218,0)) -> Switzerland
B13: Top 10 Countries — Expansion Affordability Score (Full Data Only)
B14: Rank | C14: Country | D14: Region | E14: Score
B15: 1 | C15: =INDEX(Clean_Data!A$2:A$218,MATCH(F15,Clean_Data!U$2:U$218,0)) -> Switzerland | D15: =INDEX(Clean_Data!B$2:B$218,MATCH(F15,Clean_Data!U$2:U$218,0)) -> Europe & Central Asia | E15: =INDEX(Clean_Data!T$2:T$218,MATCH(F15,Clean_Data!U$2:U$218,0)) -> 70.5 | F15: =LARGE(Clean_Data!U$2:U$218,B15) -> 70.500019
B16: 2 | C16: =INDEX(Clean_Data!A$2:A$218,MATCH(F16,Clean_Data!U$2:U$218,0)) -> Germany | D16: =INDEX(Clean_Data!B$2:B$218,MATCH(F16,Clean_Data!U$2:U$218,0)) -> Europe & Central Asia | E16: =INDEX(Clean_Data!T$2:T$218,MATCH(F16,Clean_Data!U$2:U$218,0)) -> 69.9 | F16: =LARGE(Clean_Data!U$2:U$218,B16) -> 69.900007
B17: 3 | C17: =INDEX(Clean_Data!A$2:A$218,MATCH(F17,Clean_Data!U$2:U$218,0)) -> Denmark | D17: =INDEX(Clean_Data!B$2:B$218,MATCH(F17,Clean_Data!U$2:U$218,0)) -> Europe & Central Asia | E17: =INDEX(Clean_Data!T$2:T$218,MATCH(F17,Clean_Data!U$2:U$218,0)) -> 69.9 | F17: =LARGE(Clean_Data!U$2:U$218,B17) -> 69.900005
B18: 4 | C18: =INDEX(Clean_Data!A$2:A$218,MATCH(F18,Clean_Data!U$2:U$218,0)) -> Canada | D18: =INDEX(Clean_Data!B$2:B$218,MATCH(F18,Clean_Data!U$2:U$218,0)) -> North America | E18: =INDEX(Clean_Data!T$2:T$218,MATCH(F18,Clean_Data!U$2:U$218,0)) -> 69.4 | F18: =LARGE(Clean_Data!U$2:U$218,B18) -> 69.400003
B19: 5 | C19: =INDEX(Clean_Data!A$2:A$218,MATCH(F19,Clean_Data!U$2:U$218,0)) -> Afghanistan | D19: =INDEX(Clean_Data!B$2:B$218,MATCH(F19,Clean_Data!U$2:U$218,0)) -> Middle East, North Africa, Afghanistan & Pakistan | E19: =INDEX(Clean_Data!T$2:T$218,MATCH(F19,Clean_Data!U$2:U$218,0)) -> 69.4 | F19: =LARGE(Clean_Data!U$2:U$218,B19) -> 69.4
B20: 6 | C20: =INDEX(Clean_Data!A$2:A$218,MATCH(F20,Clean_Data!U$2:U$218,0)) -> Norway | D20: =INDEX(Clean_Data!B$2:B$218,MATCH(F20,Clean_Data!U$2:U$218,0)) -> Europe & Central Asia | E20: =INDEX(Clean_Data!T$2:T$218,MATCH(F20,Clean_Data!U$2:U$218,0)) -> 69.2 | F20: =LARGE(Clean_Data!U$2:U$218,B20) -> 69.200015
B21: 7 | C21: =INDEX(Clean_Data!A$2:A$218,MATCH(F21,Clean_Data!U$2:U$218,0)) -> France | D21: =INDEX(Clean_Data!B$2:B$218,MATCH(F21,Clean_Data!U$2:U$218,0)) -> Europe & Central Asia | E21: =INDEX(Clean_Data!T$2:T$218,MATCH(F21,Clean_Data!U$2:U$218,0)) -> 68.9 | F21: =LARGE(Clean_Data!U$2:U$218,B21) -> 68.900007
B22: 8 | C22: =INDEX(Clean_Data!A$2:A$218,MATCH(F22,Clean_Data!U$2:U$218,0)) -> Italy | D22: =INDEX(Clean_Data!B$2:B$218,MATCH(F22,Clean_Data!U$2:U$218,0)) -> Europe & Central Asia | E22: =INDEX(Clean_Data!T$2:T$218,MATCH(F22,Clean_Data!U$2:U$218,0)) -> 68.5 | F22: =LARGE(Clean_Data!U$2:U$218,B22) -> 68.50001
B23: 9 | C23: =INDEX(Clean_Data!A$2:A$218,MATCH(F23,Clean_Data!U$2:U$218,0)) -> Portugal | D23: =INDEX(Clean_Data!B$2:B$218,MATCH(F23,Clean_Data!U$2:U$218,0)) -> Europe & Central Asia | E23: =INDEX(Clean_Data!T$2:T$218,MATCH(F23,Clean_Data!U$2:U$218,0)) -> 68.4 | F23: =LARGE(Clean_Data!U$2:U$218,B23) -> 68.400016
B24: 10 | C24: =INDEX(Clean_Data!A$2:A$218,MATCH(F24,Clean_Data!U$2:U$218,0)) -> Thailand | D24: =INDEX(Clean_Data!B$2:B$218,MATCH(F24,Clean_Data!U$2:U$218,0)) -> East Asia & Pacific | E24: =INDEX(Clean_Data!T$2:T$218,MATCH(F24,Clean_Data!U$2:U$218,0)) -> 68.3 | F24: =LARGE(Clean_Data!U$2:U$218,B24) -> 68.300019
